WordSimilarity-0.0.3.dist-info/DESCRIPTION.rst
WordSimilarity-0.0.3.dist-info/METADATA
WordSimilarity-0.0.3.dist-info/RECORD
WordSimilarity-0.0.3.dist-info/WHEEL
WordSimilarity-0.0.3.dist-info/metadata.json
WordSimilarity-0.0.3.dist-info/top_level.txt
WordSimilarity-0.0.3.dist-info/zip-safe
data/cilin_ex.txt
word_similarity/__init__.py
